slack_utils/__init__.py
slack_utils/challenge.py
slack_utils/exceptions.py
slack_utils/signature.py
slack_utils-0.2.1.dist-info/AUTHORS.rst
slack_utils-0.2.1.dist-info/LICENSE
slack_utils-0.2.1.dist-info/METADATA
slack_utils-0.2.1.dist-info/WHEEL
slack_utils-0.2.1.dist-info/top_level.txt
slack_utils-0.2.1.dist-info/RECORD
