Metadata-Version: 2.1
Name: slack-utils
Version: 0.2.1
Summary: Various Slack utils
Home-page: https://github.com/wilgucki/slack_utils
Author: kopytko
Author-email: mwilgucki@gmail.com
License: MIT license
Keywords: slack_utils
Platform: UNKNOWN
Classifier: Development Status :: 4 - Beta
Classifier: Intended Audience :: Developers
Classifier: License :: OSI Approved :: MIT License
Classifier: Natural Language :: English
Classifier: Programming Language :: Python :: 3
Classifier: Programming Language :: Python :: 3.6
Classifier: Programming Language :: Python :: 3.7
Classifier: Programming Language :: Python :: 3.8
Requires-Python: >=3.5
